latex2md/__init__.py
latex2md/cli.py
latex2md/converter.py
latex2md-0.1.1.dist-info/LICENSE
latex2md-0.1.1.dist-info/METADATA
latex2md-0.1.1.dist-info/WHEEL
latex2md-0.1.1.dist-info/entry_points.txt
latex2md-0.1.1.dist-info/top_level.txt
latex2md-0.1.1.dist-info/RECORD
