Metadata-Version: 2.2
Name: latex2md
Version: 0.1.1
Summary: A tool to convert LaTeX documents to Markdown format
Home-page: https://github.com/yourusername/latex2md
Author: ccchen
Author-email: 1421243966@qq.com
Classifier: Programming Language :: Python :: 3
Classifier: License :: OSI Approved :: MIT License
Classifier: Operating System :: OS Independent
Requires-Python: >=3.6
License-File: LICENSE
